hydra_client/__init__.py
hydra_client/api.py
hydra_client/common.py
hydra_client/consent.py
hydra_client/exceptions.py
hydra_client/login.py
hydra_client/logout.py
hydra_client/model.py
hydra_client/oauth2.py
hydra_client/utils.py
hydra_client/version.py
hydra_client-0.5.1.dist-info/WHEEL
hydra_client-0.5.1.dist-info/METADATA
hydra_client-0.5.1.dist-info/RECORD
